example/__init__.py
example/ex1.py
pyqt6_forms/__init__.py
pyqt6_forms/custom_qwidgets.py
pyqt6_forms/datatypes.py
pyqt6_forms/form.py
pyqt6_forms/forms.py
pyqt6_forms-0.3.0.dist-info/LICENSE
pyqt6_forms-0.3.0.dist-info/METADATA
pyqt6_forms-0.3.0.dist-info/WHEEL
pyqt6_forms-0.3.0.dist-info/top_level.txt
pyqt6_forms-0.3.0.dist-info/RECORD
